MallGoEmail/backend.py
MallGoEmail/conf.py
MallGoEmail/emailmessage.py
MallGoEmail/send.py
mallgo_email-0.3.0.dist-info/METADATA
mallgo_email-0.3.0.dist-info/WHEEL
mallgo_email-0.3.0.dist-info/top_level.txt
mallgo_email-0.3.0.dist-info/RECORD
