Metadata-Version: 2.1
Name: mallgo-email
Version: 0.3.0
Summary: This is a library developed by the Inkremental team in order to use integrate the mallgo-email-service on django projects.
Author-email: Inkremental SAS <tecnologia@inkremental.co>
Project-URL: Homepage, https://inkremental.co
Classifier: Programming Language :: Python :: 3
Requires-Python: >=3.6
